<?xml version="1.0" encoding="UTF-8"?>
<objects serializationModel="Studio.02.02.00">
	<object class="AudioFile" id="{bcbe7534-d377-4c32-9751-cffc591ff6dc}">
		<property name="assetPath">
			<value>FOOTSTEPS/WOOD/WOOD-004.wav</value>
		</property>
		<property name="frequencyInKHz">
			<value>44.0999985</value>
		</property>
		<property name="channelCount">
			<value>1</value>
		</property>
		<property name="length">
			<value>1.4548072562358276</value>
		</property>
		<relationship name="masterAssetFolder">
			<destination>{6bf31780-b44f-44f2-9da0-9e8c76c21ab6}</destination>
		</relationship>
	</object>
</objects>
